{
	"metaDataVersion": "1.0.0",
	"category": "com.microchip.ide.project",
	"content": {
		"metaDataVersion": "1.1.0",
		"name": "com.microchip.mcu32.mplabx.project.usb_apps_host_msd_basic_sam_g55_xpro",
		"version": "3.0.0",
		"displayName": "MSD Basic Example (msd_basic) Example for SAM G5x Family",
		"projectName": "msd_basic_sam_g55_xpro",
		"shortDescription": "This application demonstrates the use of the MSD Host Class Driver to write a file to a USB Flash drive. The application uses the USB Host_layer , MSD class driver and the MPLAB Harmony File System Framework to enumerate a USB Flash drive and to write a file to it.",
		"ide": {
			"name": "MPLABX",
			"semverRange": ">=5.45.0"
		},
		"compiler": [
			{
				"name": "XC32",
				"semverRange": ">=2.50.0"
			}
		],
		"dfp": {
			"name": "SAMG_DFP",
			"semverRange": "^3.3.42"
		},
		"configurator": {
			"name": "MHC",
			"semverRange": ">=3.6.1"
		},
		"device": {
			"metaDataVersion": "1.0.0",
			"category": "com.microchip.portal.contentRef",
			"content": {
				"metaDataVersion": "1.0.0",
				"category": "com.microchip.device",
				"name": "ATSAMG55J19",
				"versionRange": "*"
			}
		},
		"author": "Microchip",
		"subcategories": [
			[
				"Development Kit", "SAM G55 Xplained Pro Evaluation Kit"
			],
			[
				"Harmony", "Middleware", "USB", "MSD_BASIC"
			],
			[
				"Middleware", "USB", "MSD_BASIC"
			]
		],
		"peripherals": [
			"USB"
		],
		"keywords": [
			"MHC",
			"Harmony",
			"Middleware",
			"USB",
			"ATSAMG55J19",
			"SAM G5x Family",
			"USB"
		],
		"additionalData": {
			"longDescription": {
				"metaDataVersion": "1.0.0",
				"category": "com.microchip.portal.fileRef",
				"content": {
					"metaDataVersion": "1.0.0",
					"fileName": "./../../readme.md",
					"mimeType": "text/markdown"
				}
			}
		}
	}
}